<annotation>
	<folder>JPEGImages</folder>
	<filename>garbage49.jpg</filename>
	<path>D:\document\PaddleDetection-release-2.6\dataset\voc\JPEGImages\garbage49.jpg</path>
	<source>
		<database>Unknown</database>
	</source>
	<size>
		<width>471</width>
		<height>317</height>
		<depth>3</depth>
	</size>
	<segmented>0</segmented>
	<object>
		<name>garbage</name>
		<pose>Unspecified</pose>
		<truncated>0</truncated>
		<difficult>0</difficult>
		<bndbox>
			<xmin>192</xmin>
			<ymin>53</ymin>
			<xmax>349</xmax>
			<ymax>221</ymax>
		</bndbox>
	</object>
	<object>
		<name>garbage</name>
		<pose>Unspecified</pose>
		<truncated>0</truncated>
		<difficult>0</difficult>
		<bndbox>
			<xmin>11</xmin>
			<ymin>75</ymin>
			<xmax>136</xmax>
			<ymax>178</ymax>
		</bndbox>
	</object>
</annotation>
